{
  "name": "ceruledge",
  "id": 1005,
  "stock": true,
  "base_experience": 64,
  "size": {
    "height": 1.6
  },
  "mass": 62,
  "is_default": true,
  "capture_rate": 25,
  "base_happiness": 20,
  "growth_rate": "slow",
  "gender_rate": 30,
  "stats": {
    "hp": 75,
    "attack": 125,
    "defense": 80,
    "special_attack": 60,
    "special_defense": 100,
    "speed": 85
  },
  "evs": {
    "special_attack": 2
  },
  "types": [
    "fire",
	"ghost"
  ],
  "abilities": {
    "normal": [
      "flash-fire",
    ],
    "hidden": [
	  "weak-armor"
	]
  },
  "moves": {
    "level_up": [
      {
        "L": 1,
        "moves": [
          "leer",
		  "ember",
		  "mystical-fire",
		  "astonish",
		  "wide-guard"
        ]
      },
      {
        "L": 8,
        "moves": [
          "clear-smog"
        ]
      },
      {
        "L": 12,
        "moves": [
          "fire-spin"
        ]
      },
      {
        "L": 16,
        "moves": [
          "will-o-wisp"
        ]
      },
      {
        "L": 20,
        "moves": [
          "night-shade"
        ]
      },
      {
        "L": 24,
        "moves": [
          "flame-charde"
        ]
      },
      {
        "L": 28,
        "moves": [
          "incinerate"
        ]
      },
      {
        "L": 32,
        "moves": [
          "lava-plume"
        ]
      },
      {
        "L": 37,
        "moves": [
          "swords-dance"
        ]
      },
      {
        "L": 42,
        "moves": [
          "ally-switch"
        ]
      },
      {
        "L": 48,
        "moves": [
          "bitter-blade"
        ]
      },
      {
        "L": 56,
        "moves": [
          "psycho-cut"
        ]
      },
      {
        "L": 62,
        "moves": [
          "flare-blitz"
        ]
      }
    ],
    "misc": [
	  "swords-dance",
	"take-down",
	"flamethrower",
	"fire-spin",
	"night-shade",
	"confuse-ray",
	"light-screen",
	"reflect",
	"fire-blast",
	"rest",
	"substitute",
	"protect",
	"endure",
	"false-swipe",
	"sleep-talk",
	"sunny-day",
	"shadow-ball",
	"heat-wave",
	"will-o-wisp",
	"facade",
	"taunt",
	"helping-hand",
	"brick-break",
	"overheat",
	"iron-defense",
	"dragon-claw",
	"bulk-up",
	"close-combat",
	"fling",
	"flare-blitz",
	"poison-jab",
	"x-scissor",
	"shadow-claw",
	"iron-head",
	"flame-charge",
	"stored-power",
	"hex",
	"phantom-force",
	"tera-blast"
    ]
  },
  "loot_table": "pokecube:entities/coal_rabbit_2"
}