{
	"credit": "Made with Blockbench",
	"parent": "minecraft:item/handheld",
	"textures": {
		"layer0": "pokecube_legends:item/zacian_sword"
	},
	"display": {
		"thirdperson_righthand": {
			"rotation": [0, -90, 55],
			"translation": [0, 8, 1],
			"scale": [1.5, 1.5, 0.85]
		},
		"thirdperson_lefthand": {
			"rotation": [0, 90, -55],
			"translation": [0, 8, 1],
			"scale": [1.5, 1.5, 0.85]
		},
		"firstperson_righthand": {
			"rotation": [0, -90, 25],
			"translation": [6, 2, -5],
			"scale": [1.5, 1.5, 0.68]
		},
		"firstperson_lefthand": {
			"rotation": [0, 90, -25],
			"translation": [6, 2, -5],
			"scale": [1.5, 1.5, 0.68]
		},
		"ground": {
			"rotation": [90, 0, 0],
			"translation": [0, -5, 0],
			"scale": [1.5, 1.5, 1]
		},
		"gui": {
			"scale": [1.35, 1.35, 1.35]
		},
		"head": {
			"rotation": [0, 0, -135],
			"translation": [0, 14, -1],
			"scale": [1.5, 1.5, 1]
		},
		"fixed": {
			"rotation": [0, 180, 0],
			"scale": [1.5, 1.5, 1]
		}
	}
}