{
  "name": "ice-punch",
  "animations": [
    {
      "preset": "cartFunc:pcrit:d1.5:w1:f(0.5-rand())*(1),(0.5-rand())*(1),(0.5-rand())*(1)",
      "duration": "5",
      "starttick": "0",
      "sound": "pokecube:moves.woodenhammer",
      "soundSource": true,
      "soundTarget": false,
      "volume": 1.0,
      "pitch": 1.5
    },
    {
      "preset": "cartFunc:pmisc:d1:w1:l5:f(0.5-rand())*(1),(0.5-rand())*(1),(0.5-rand())*(1)",
      "duration": "5",
      "starttick": "0",
      "sound": "pokecube:moves.iceball",
      "soundSource": true,
      "soundTarget": false,
      "volume": 1.0,
      "pitch": 1.0
    }
  ]
}