{
  "name": "mega-drain",
  "animations": [
    {
      "preset": "beam",
      "duration": 5,
      "starttick": 0,
      "volume": 1.0,
      "pitch": 0.9,
      "sound": "pokecube:moves.waterpulse",
      "soundSource": true,
      "soundTarget": false,
      "preset_values": {}
    },
    {
      "preset": "cartFunc",
      "duration": 5,
      "starttick": 4,
      "volume": 1.0,
      "pitch": 1.0,
      "sound": "pokecube:moves.waterpulse",
      "soundSource": true,
      "soundTarget": false,
      "preset_values": {
        "particle": "end_rod",
        "density": 2.0,
        "width": 1.0,
        "reverse": true,
        "f_x": "(0.5-rand())*(1)",
        "f_y": "(0.5-rand())*(1)",
        "f_z": "(0.5-rand())*(1)"
      }
    }
  ]
}