{
  "display": {
    "icon": {
      "item": "pokecube:pokecube"
    },
    "title": {
      "translate": "achievement.pokecube.catch",
      "with": [
        {
          "translate": "pkmn.bayleef.name"
        }
      ]
    },
    "description": {
      "translate": "achievement.pokecube.catch.desc",
      "with": [
        {
          "translate": "pkmn.bayleef.name"
        }
      ]
    }
  },
  "criteria": {
    "catch_bayleef": {
      "trigger": "pokecube:catch",
      "conditions": {
        "lenient": true,
        "entry": "bayleef"
      }
    }
  },
  "parent": "pokecube_mobs:capture/catch_chikorita"
}