{
  "name": "grass-knot",
  "id": 447,
  "pp": 20,
  "priority": 0,
  "type": "grass",
  "accuracy": 100,
  "target": "selected-pokemon",
  "damage_class": "special",
  "flavor_text": "The user snares the target with grass and trips it. The heavier the target, the greater the move’s power.",
  "move_category": "damage",
  "ailment": "none",
  "effect_text_extend": "Inflicts regular damage.  Power increases with the target's weight in kilograms, to a maximum of 120.\n\nTarget's weight | Power\n--------------- | ----:\nUp to 10kg      |    20\nUp to 25kg      |    40\nUp to 50kg      |    60\nUp to 100kg     |    80\nUp to 200kg     |   100\nAbove 200kg     |   120\n",
  "effect_text_simple": "Inflicts more damage to heavier targets, with a maximum of 120 power."
}