{
  "display": {
    "icon": {
      "item": "pokecube:pokecube"
    },
    "title": {
      "translate": "achievement.pokecube.hatch",
      "with": [
        {
          "translate": "entity.pokecube.cobalion"
        }
      ]
    },
    "description": {
      "translate": "achievement.pokecube.hatch.desc",
      "with": [
        {
          "translate": "entity.pokecube.cobalion"
        }
      ]
    },
    "frame": "challenge"
  },
  "criteria": {
    "hatch_cobalion": {
      "trigger": "pokecube:hatch",
      "conditions": {
        "entry": "cobalion"
      }
    }
  },
  "parent": "pokecube_mobs:hatch/root"
}