
{
    "_comment": "Pokecube Guide Book",
    "pokecube.infobook1.json": "{pages:[\"[\\\"\\\",{\\\"text\\\":\\\"Pokecube\\\",\\\"bold\\\":true,\\\"underlined\\\":true,\\\"color\\\":\\\"red\\\"},{\\\"text\\\":\\\" \\\",\\\"color\\\":\\\"reset\\\"},{\\\"text\\\":\\\"指南\\\",\\\"bold\\\":true,\\\"underlined\\\":true,\\\"color\\\":\\\"black\\\"}]\",\"[\\\"\\\",{\\\"text\\\":\\\"目录\\\",\\\"bold\\\":true,\\\"color\\\":\\\"black\\\"},{\\\"text\\\":\\\"\\\\n\\\\n\\\",\\\"color\\\":\\\"reset\\\"},{\\\"text\\\":\\\"开始你的宝可梦之旅\\\",\\\"bold\\\":true,\\\"color\\\":\\\"dark_blue\\\",\\\"clickEvent\\\":{\\\"action\\\":\\\"change_page\\\",\\\"value\\\":3}},{\\\"text\\\":\\\"\\\\n\\\",\\\"color\\\":\\\"reset\\\"},{\\\"text\\\":\\\"精灵球\\\",\\\"bold\\\":true,\\\"color\\\":\\\"dark_green\\\",\\\"clickEvent\\\":{\\\"action\\\":\\\"change_page\\\",\\\"value\\\":5}},{\\\"text\\\":\\\"\\\\n\\\",\\\"color\\\":\\\"reset\\\"},{\\\"text\\\":\\\"宝可梦手表\\\",\\\"bold\\\":true,\\\"color\\\":\\\"dark_aqua\\\",\\\"clickEvent\\\":{\\\"action\\\":\\\"change_page\\\",\\\"value\\\":10}},{\\\"text\\\":\\\"\\\\n\\\",\\\"color\\\":\\\"reset\\\"},{\\\"text\\\":\\\"传说的宝可梦\\\",\\\"bold\\\":true,\\\"color\\\":\\\"dark_purple\\\",\\\"clickEvent\\\":{\\\"action\\\":\\\"change_page\\\",\\\"value\\\":14}},{\\\"text\\\":\\\"\\\\n\\\",\\\"color\\\":\\\"reset\\\"},{\\\"text\\\":\\\"超级进化\\\",\\\"bold\\\":true,\\\"color\\\":\\\"gold\\\",\\\"clickEvent\\\":{\\\"action\\\":\\\"change_page\\\",\\\"value\\\":17}},{\\\"text\\\":\\\"\\\\n\\\",\\\"color\\\":\\\"reset\\\"},{\\\"text\\\":\\\"化石宝可梦\\\",\\\"bold\\\":true,\\\"color\\\":\\\"dark_red\\\",\\\"clickEvent\\\":{\\\"action\\\":\\\"change_page\\\",\\\"value\\\":18}},{\\\"text\\\":\\\"\\\\n\\\",\\\"color\\\":\\\"reset\\\"},{\\\"text\\\":\\\"树果\\\",\\\"bold\\\":true,\\\"color\\\":\\\"dark_gray\\\",\\\"clickEvent\\\":{\\\"action\\\":\\\"change_page\\\",\\\"value\\\":19}},{\\\"text\\\":\\\"\\\\n\\\",\\\"color\\\":\\\"reset\\\"},{\\\"text\\\":\\\"招式学习器\\\",\\\"bold\\\":true,\\\"color\\\":\\\"blue\\\",\\\"clickEvent\\\":{\\\"action\\\":\\\"change_page\\\",\\\"value\\\":20}},{\\\"text\\\":\\\"\\\\n\\\",\\\"color\\\":\\\"reset\\\"},{\\\"text\\\":\\\"个体值和基础得点\\\",\\\"bold\\\":true,\\\"color\\\":\\\"aqua\\\",\\\"clickEvent\\\":{\\\"action\\\":\\\"change_page\\\",\\\"value\\\":21}},{\\\"text\\\":\\\"\\\\n\\\",\\\"color\\\":\\\"reset\\\"},{\\\"text\\\":\\\"百科\\\",\\\"bold\\\":true,\\\"color\\\":\\\"green\\\",\\\"clickEvent\\\":{\\\"action\\\":\\\"change_page\\\",\\\"value\\\":22}}]\",\"[\\\"\\\",{\\\"text\\\":\\\"开始你的宝可梦之旅\\\",\\\"bold\\\":true,\\\"color\\\":\\\"dark_blue\\\"},{\\\"text\\\":\\\"\\\\n\\\\n\\\",\\\"color\\\":\\\"reset\\\"},{\\\"text\\\":\\\" 当你加入任何一个世界或服务器时，你会收到最初的伙伴、精灵手表、背包和10个精灵球。\\\\n 你可以将能被宝可梦携带的物品存放在背包里，其中大多是与本MOD相关的物品。\\\",\\\"color\\\":\\\"dark_blue\\\"}]\",\"{\\\"text\\\":\\\" 要与宝可梦战斗，你可以将对着它丢出你的宝可梦，或者随意把精灵球丢出，然后对着它按下让宝可梦攻击的指令键。\\\\n 你可以用按键收回宝可梦，如果你找不到它在哪里，用指令/pokerecall也可以召回（译注：善用TAB补全参数）。\\\",\\\"color\\\":\\\"dark_blue\\\"}\",\"[\\\"\\\",{\\\"text\\\":\\\"Pokecubes\\\",\\\"bold\\\":true,\\\"color\\\":\\\"dark_green\\\"},{\\\"text\\\":\\\"\\\\n\\\\n 不同的精灵球有不同的效果，精灵球、超级球、高级球和大师球可以从商人NPC处购买，也可能在村庄里找到，但自己制作精灵球要容易得多。\\\",\\\"color\\\":\\\"dark_green\\\"}]\",\"{\\\"text\\\":\\\"精灵球：1倍的捕获率。\\\\n\\\\n超级球：1.5倍的捕获率。\\\\n\\\\n高级球：2倍的捕获率。\\\\n\\\\n大师球：能收服任何宝可梦（对于特殊的宝可梦可能需要先完成前置要求）。\\\",\\\"color\\\":\\\"dark_green\\\"}\",\"[\\\"\\\",{\\\"text\\\":\\\"黑暗球：在夜间或者低亮度环境下捕获率为4倍。\\\",\\\"color\\\":\\\"dark_green\\\"},{\\\"text\\\":\\\"\\\\n\\\\n\\\",\\\"color\\\":\\\"reset\\\"},{\\\"text\\\":\\\"先机球：对刚生成的宝可梦捕获率为4倍。\\\",\\\"color\\\":\\\"dark_green\\\"},{\\\"text\\\":\\\"\\\\n\\\\n\\\",\\\"color\\\":\\\"reset\\\"},{\\\"text\\\":\\\"计时球：对老的宝可梦有更高的捕获率。（译注：应指生成时间）\\\",\\\"color\\\":\\\"dark_green\\\"}]\",\"[\\\"\\\",{\\\"text\\\":\\\"捕网球：对水系和虫系的宝可梦捕获率为3倍。\\\",\\\"color\\\":\\\"dark_green\\\"},{\\\"text\\\":\\\"\\\\n\\\\n\\\",\\\"color\\\":\\\"reset\\\"},{\\\"text\\\":\\\"巢穴球：更容易收服等级低的宝可梦。\\\",\\\"color\\\":\\\"dark_green\\\"},{\\\"text\\\":\\\"\\\\n\\\\n\\\",\\\"color\\\":\\\"reset\\\"},{\\\"text\\\":\\\"重复球：对已收服过的宝可梦捕获率为3倍。\\\",\\\"color\\\":\\\"dark_green\\\"}]\",\"[\\\"\\\",{\\\"text\\\":\\\"纪念球和贵重球的捕获率为1倍。\\\",\\\"color\\\":\\\"dark_green\\\"},{\\\"text\\\":\\\"\\\\n\\\\n\\\",\\\"color\\\":\\\"reset\\\"},{\\\"text\\\":\\\"夺取球：用于收服黑暗宝可梦。\\\",\\\"color\\\":\\\"dark_green\\\"},{\\\"text\\\":\\\"\\\\n\\\\n\\\",\\\"color\\\":\\\"reset\\\"},{\\\"text\\\":\\\"潜水球：在水下对水系宝可梦的捕获率为3.5倍。\\\",\\\"color\\\":\\\"dark_green\\\"}]\",\"[\\\"\\\",{\\\"text\\\":\\\"宝可梦手表\\\",\\\"bold\\\":true,\\\"color\\\":\\\"dark_aqua\\\"},{\\\"text\\\":\\\"\\\\n\\\\n\\\",\\\"color\\\":\\\"reset\\\"},{\\\"text\\\":\\\" 宝可梦手表整合了图鉴的功能，在图鉴的第一页你可以看到宝可梦的能力。\\\\n 对着宝可梦右键时，第二页会展示特性、性格等状态信息。\\\\n 在第三页你可以看到这种宝可梦可以学习的招式（对着宝可梦使用则显示它记住的招式）。\\\\n 第四页展示这种宝可梦的栖息地和生成率。\\\",\\\"color\\\":\\\"dark_aqua\\\"}]\",\"[\\\"\\\",{\\\"text\\\":\\\" 第五页列出了可以与之配种的宝可梦种类。\\\\n 第六页则是关于其进化家族的信息。\\\",\\\"color\\\":\\\"dark_aqua\\\"},{\\\"text\\\":\\\"\\\\n\\\\n\\\",\\\"color\\\":\\\"reset\\\"},{\\\"text\\\":\\\" 图鉴的第一页对某一只宝可梦打开会展示个体值、基础得点等详细数值信息，否则展示种族值。\\\",\\\"color\\\":\\\"dark_aqua\\\"}]\",\"[\\\"\\\",{\\\"text\\\":\\\" 在宝可梦手表主页的进度页面，有时手表会发出信息，此时点击检查进度可以收到一些礼物。\\\",\\\"color\\\":\\\"dark_aqua\\\"},{\\\"text\\\":\\\"\\\\n\\\",\\\"color\\\":\\\"reset\\\"},{\\\"text\\\":\\\" 当你你收服了一定种类的新宝可梦之后就会收到礼物，获得的礼物顺序是：指南书、学习装置、大师球、闪耀护符。\\\",\\\"color\\\":\\\"dark_aqua\\\"}]\",\"{\\\"text\\\":\\\"最后一份礼物在完成图鉴的一半时获得。\\\",\\\"color\\\":\\\"dark_aqua\\\"}\",\"[\\\"\\\",{\\\"text\\\":\\\"传说的宝可梦\\\",\\\"bold\\\":true,\\\"color\\\":\\\"dark_purple\\\"},{\\\"text\\\":\\\"\\\\n\\\\n\\\",\\\"color\\\":\\\"reset\\\"},{\\\"text\\\":\\\" 有一些宝可梦仍然没有办法获得，但大部分生成在特定的生物群落，服务器可以设置他们可以生成的最小等级。\\\\n 许多传说的宝可梦和幻之宝可梦具有特殊的收服要求，在宝可梦手表的图鉴中可以查看是否已经满足条件。条件可能与服务器或当前版本相关，此处仅举例，请以图鉴提示为准。\\\\n\\\\n 要取得时拉比的认可，你必须先收服一定比例的草系宝可梦\\\",\\\"color\\\":\\\"dark_purple\\\"}]\",\"[\\\"\\\",{\\\"text\\\":\\\" 要取得凤王的认可，你必须先收服传说的三圣兽。\\\",\\\"color\\\":\\\"dark_purple\\\"},{\\\"text\\\":\\\"\\\\n\\\\n\\\",\\\"color\\\":\\\"reset\\\"},{\\\"text\\\":\\\" 要取得雷公的认可，你必须先收服图鉴中一定比例的电属性宝可梦。\\\",\\\"color\\\":\\\"dark_purple\\\"},{\\\"text\\\":\\\"\\\\n\\\\n\\\",\\\"color\\\":\\\"reset\\\"},{\\\"text\\\":\\\" 要取得水君的认可，你必须先收服图鉴中一定比例的水属性宝可梦。\\\",\\\"color\\\":\\\"dark_purple\\\"},{\\\"text\\\":\\\"\\\\n\\\\n\\\",\\\"color\\\":\\\"reset\\\"},{\\\"text\\\":\\\" 要取得炎帝的认可，你必须先收服图鉴中一定比例的火属性宝可梦。\\\",\\\"color\\\":\\\"dark_purple\\\"}]\",\"[\\\"\\\",{\\\"text\\\":\\\" 要取得梦幻的认可，你必须先得到闪耀护符。\\\",\\\"color\\\":\\\"dark_purple\\\"},{\\\"text\\\":\\\"\\\\n\\\\n\\\",\\\"color\\\":\\\"reset\\\"},{\\\"text\\\":\\\" 要取得传说的巨人的认可（以及召唤物），你需要收服古空棘鱼和吼鲸王。\\\",\\\"color\\\":\\\"dark_purple\\\"},{\\\"text\\\":\\\"\\\\n\\\\n\\\",\\\"color\\\":\\\"reset\\\"},{\\\"text\\\":\\\" 要取得固拉多的认可，你必须先收服图鉴中一定比例的地面属性宝可梦并击败过一定比例的水属性宝可梦，盖欧卡则相反。\\\",\\\"color\\\":\\\"dark_purple\\\"}]\",\"[\\\"\\\",{\\\"text\\\":\\\"超级进化\\\",\\\"bold\\\":true,\\\"color\\\":\\\"gold\\\"},{\\\"text\\\":\\\"\\\\n\\\\n\\\",\\\"color\\\":\\\"reset\\\"},{\\\"text\\\":\\\" 想要让宝可梦超级进化需要佩戴超级服饰并让宝可梦携带对应的超级石,然后按下超级进化键（默认M）\\\",\\\"color\\\":\\\"gold\\\"}]\",\"[\\\"\\\",{\\\"text\\\":\\\"化石宝可梦\\\",\\\"bold\\\":true,\\\"color\\\":\\\"dark_red\\\"},{\\\"text\\\":\\\"\\\\n\\\\n 要得到化石宝可梦，你需要在沙漠丘陵、海洋、丛林或丛林丘陵中找到化石并制作一个化石机器，然后把化石放进机器里。\\\",\\\"color\\\":\\\"dark_red\\\"}]\",\"[\\\"\\\",{\\\"text\\\":\\\"树果\\\",\\\"bold\\\":true,\\\"color\\\":\\\"dark_gray\\\"},{\\\"text\\\":\\\"\\\\n\\\\n\\\",\\\"color\\\":\\\"reset\\\"},{\\\"text\\\":\\\" 击败宝可梦可以找到树果，通过种植可以得到更多。\\\\n每种树果都有不同效果。\\\\n 你可以把树果放在宝可梦的储存空间里，这样宝可梦在饿了的时候会自己吃掉树果。\\\",\\\"color\\\":\\\"dark_gray\\\"}]\",\"[\\\"\\\",{\\\"text\\\":\\\"招式学习器\\\",\\\"bold\\\":true,\\\"color\\\":\\\"blue\\\"},{\\\"text\\\":\\\"\\\\n\\\\n\\\",\\\"color\\\":\\\"reset\\\"},{\\\"text\\\":\\\" 招式学习器可在招式学习器制作器中制作。你可以制作招式教学机，如果你把它放在一台电脑的侧面，它可以识别你的电脑中的宝可梦和你的招式学习器。你可以将招式学习器（不一定要是空白的）放在招式学习器制作器中，从你的宝可梦记住的招式中选择一个记录下来。\\\",\\\"color\\\":\\\"blue\\\"}]\",\"[\\\"\\\",{\\\"text\\\":\\\"个体值和基础得点\\\",\\\"bold\\\":true,\\\"color\\\":\\\"aqua\\\"},{\\\"text\\\":\\\"\\\\n\\\\n个体值是宝可梦的遗传属性，介于0~31之间，只能通过育种来改善，或者收服新的宝可梦。\\\\n 你的宝可梦会根据它打败的宝可梦的种类获得基础得点（旧译学习力、努力值），这将以一定的方式提高宝可梦的属性。\\\",\\\"color\\\":\\\"aqua\\\"},{\\\"text\\\":\\\"http://pokemondb.net/ev/all\\\",\\\"underlined\\\":true,\\\"color\\\":\\\"dark_blue\\\",\\\"clickEvent\\\":{\\\"action\\\":\\\"open_url\\\",\\\"value\\\":\\\"http://pokemondb.net/ev/all\\\"}},{\\\"text\\\":\\\" 在这里你可以看到击败宝可梦后获得的基础得点。\\\",\\\"color\\\":\\\"aqua\\\"}]\",\"[\\\"\\\",{\\\"text\\\":\\\"百科\\\",\\\"bold\\\":true,\\\"color\\\":\\\"green\\\"},{\\\"text\\\":\\\"\\\\n\\\\n 如果你想了解更多关于Pokecube的信息，这里有两个英文百科网站：\\\",\\\"color\\\":\\\"green\\\"},{\\\"text\\\":\\\"\\\\n\\\\n\\\",\\\"color\\\":\\\"reset\\\"},{\\\"text\\\":\\\"https://github.com/thutmose/pokecube/wiki\\\",\\\"underlined\\\":true,\\\"color\\\":\\\"dark_blue\\\",\\\"clickEvent\\\":{\\\"action\\\":\\\"open_url\\\",\\\"value\\\":\\\"https://github.com/thutmose/pokecube/wiki\\\"}},{\\\"text\\\":\\\"\\\\n\\\\n\\\",\\\"color\\\":\\\"reset\\\"},{\\\"text\\\":\\\"pokecubemod.wikia.com/wiki/PokecubeMod_Wikia\\\",\\\"underlined\\\":true,\\\"color\\\":\\\"dark_blue\\\",\\\"clickEvent\\\":{\\\"action\\\":\\\"open_url\\\",\\\"value\\\":\\\"pokecubemod.wikia.com/wiki/PokecubeMod_Wikia\\\"}}]\"],title:\"Pokecube Guide\",author:falcojack,display:{Lore:[\"Starter Guide to Pokecube\"]}}"
}
