{
  "name": "razor-shell",
  "animations": [
    {
      "preset": "cartFunc",
      "duration": 5,
      "starttick": 0,
      "volume": 1.0,
      "pitch": 1.0,
      "sound": "pokecube:moves.dive",
      "soundSource": true,
      "soundTarget": false,
      "preset_values": {
        "particle": "droplet",
        "rgba_string": "light_blue",
        "density": 0.5,
        "width": 1.5,
        "lifetime": 70,
        "f_x": "(0.5-rand())*(1)",
        "f_y": "(0.5-rand())*(1)",
        "f_z": "(0.5-rand())*(1)"
      }
    },
    {
      "preset": "cartFunc",
      "duration": 5,
      "starttick": 0,
      "volume": 1.0,
      "pitch": 1.3,
      "sound": "pokecube:moves.slash",
      "soundSource": true,
      "soundTarget": false,
      "preset_values": {
        "particle": "sweep_attack",
        "density": 2.0
      }
    }
  ]
}